code/20_neuron_new/Accumulating_Adder.v


`timescale 1ns / 1ps

module Accumulating_Adder(


    input clk,
    input reset,
    input [31:0] a_operand,   // Input value in IEEE-754 format
    output Exception,
    output reg [31:0] result  // Output accumulated result
);

wire [31:0] operand_a, operand_b;
wire [23:0] significand_a, significand_b;
wire [24:0] significand_add;
wire [30:0] add_sum;
wire [7:0] exponent_diff;

reg [31:0] accumulator;

// Initial assignment
assign operand_a = a_operand;
assign operand_b = accumulator;

// Check for IEEE-754 special case exception
assign Exception = (&operand_a[30:23]) | (&operand_b[30:23]);

// Extract significands (add hidden bit if normalized)
assign significand_a = (|operand_a[30:23]) ? {1'b1, operand_a[22:0]} : {1'b0, operand_a[22:0]};
assign significand_b = (|operand_b[30:23]) ? {1'b1, operand_b[22:0]} : {1'b0, operand_b[22:0]};

// Match exponents by shifting
assign exponent_diff = (operand_a[30:23] > operand_b[30:23]) ? 
                        (operand_a[30:23] - operand_b[30:23]) : 
                        (operand_b[30:23] - operand_a[30:23]);

wire [23:0] aligned_a = (operand_a[30:23] > operand_b[30:23]) ? significand_a : significand_a >> exponent_diff;
wire [23:0] aligned_b = (operand_a[30:23] > operand_b[30:23]) ? significand_b >> exponent_diff : significand_b;

wire [7:0] result_exp = (operand_a[30:23] > operand_b[30:23]) ? operand_a[30:23] : operand_b[30:23];

// Add aligned significands
assign significand_add = aligned_a + aligned_b;

// Normalize result
assign add_sum[22:0] = significand_add[24] ? significand_add[23:1] : significand_add[22:0];
assign add_sum[30:23] = significand_add[24] ? (result_exp + 1) : result_exp;

wire output_sign = 1'b0;  // assume positive values only for simplicity

// Update accumulator and result on clock
always @(posedge clk or posedge reset) begin
    if (reset) begin
        accumulator <= 32'd0;
        result <= 32'd0;
    end else if (!Exception) begin
        accumulator <= {output_sign, add_sum};
        result <= accumulator;
    end else begin
        result <= 32'd0;
    end
end

endmodule

code/20_neuron_new/acc_tb.v
`timescale 1ns / 1ps
`include "acc.v"

module Accumulating_Adder_tb;

    reg clk;
    reg reset;
    reg [31:0] a_operand;
    wire [31:0] result;
    wire Exception;

    // Instantiate the DUT (Design Under Test)
    Accumulating_Adder uut (
        .clk(clk),
        .reset(reset),
        .a_operand(a_operand),
        .Exception(Exception),
        .result(result)
    );

    // Clock generation
    always #5 clk = ~clk;
// Function to convert IEEE-754 bits to real
    // Helper task to display float in hex
    task print_result;
        input [31:0] res;
        begin
            $display("Time: %0t | Result = 0x%08X", $time, res);
        end
    endtask
    initial begin
        $dumpfile("acc_tb.vcd");
        $dumpvars(0,Accumulating_Adder_tb);
    end
    initial begin
        // Initialize
        clk = 0;
        reset = 1;
        a_operand = 32'h00000000; // 0.0
        #10;

        reset = 0;

        // Add 1.0
        a_operand = 32'h3F800000; // 1.0 in IEEE-754
        #10;
        print_result(result);

        // Add 2.0
        a_operand = 32'h40000000; // 2.0 in IEEE-754
        #10;
        print_result(result);

        // Add 4.0
        a_operand = 32'h40800000; // 4.0 in IEEE-754
        #10;
        print_result(result);

        // Add 0.5
        a_operand = 32'h3F000000; // 0.5 in IEEE-754
        #10;
        print_result(result);

        // Reset
        reset = 1;
        #10;
        print_result(result);

        $finish;
    end

endmodule

code/20_neuron_new/acc_tb.vcd
$date
	Fri Apr 18 09:18:34 2025
$end
$version
	Icarus Verilog
$end
$timescale
	1ps
$end
$scope module Accumulating_Adder_tb $end
$var wire 32 ! result [31:0] $end
$var wire 1 " Exception $end
$var reg 32 # a_operand [31:0] $end
$var reg 1 $ clk $end
$var reg 1 % reset $end
$scope module uut $end
$var wire 1 " Exception $end
$var wire 32 & a_operand [31:0] $end
$var wire 1 $ clk $end
$var wire 32 ' operand_a [31:0] $end
$var wire 32 ( operand_b [31:0] $end
$var wire 1 ) output_sign $end
$var wire 1 % reset $end
$var wire 24 * significand_b [23:0] $end
$var wire 25 + significand_add [24:0] $end
$var wire 24 , significand_a [23:0] $end
$var wire 8 - result_exp [7:0] $end
$var wire 8 . exponent_diff [7:0] $end
$var wire 24 / aligned_b [23:0] $end
$var wire 24 0 aligned_a [23:0] $end
$var wire 31 1 add_sum [30:0] $end
$var reg 32 2 accumulator [31:0] $end
$var reg 32 3 result [31:0] $end
$upscope $end
$scope task print_result $end
$var reg 32 4 res [31:0] $end
$upscope $end
$upscope $end
$enddefinitions $end
#0
$dumpvars
bx 4
b0 3
b0 2
b0 1
b0 0
b0 /
b0 .
b0 -
b0 ,
b0 +
b0 *
0)
b0 (
b0 '
b0 &
1%
0$
b0 #
0"
b0 !
$end
#5000
1$
#10000
b100000000000000000000000 +
b100000000000000000000000 0
b111111100000000000000000000000 1
b100000000000000000000000 ,
b1111111 .
b1111111 -
0$
b111111100000000000000000000000 '
b111111100000000000000000000000 #
b111111100000000000000000000000 &
0%
#15000
b1000000000000000000000000000000 1
b100000000000000000000000 /
b100000000000000000000000 *
b0 .
b1000000000000000000000000 +
b100000000000000000000000 0
b111111100000000000000000000000 (
b111111100000000000000000000000 2
1$
#20000
b110000000000000000000000 +
b10000000000000000000000 /
b1000000010000000000000000000000 1
b1 .
b10000000 -
0$
b1000000000000000000000000000000 '
b1000000000000000000000000000000 #
b1000000000000000000000000000000 &
b0 4
#25000
b1000000101000000000000000000000 1
b110000000000000000000000 *
b0 .
b100000000000000000000000 0
b1010000000000000000000000 +
b110000000000000000000000 /
b111111100000000000000000000000 !
b111111100000000000000000000000 3
b1000000010000000000000000000000 (
b1000000010000000000000000000000 2
1$
#30000
b111000000000000000000000 +
b11000000000000000000000 /
b1000000111000000000000000000000 1
b1 .
b10000001 -
0$
b1000000100000000000000000000000 '
b1000000100000000000000000000000 #
b1000000100000000000000000000000 &
b111111100000000000000000000000 4
#35000
b1000001001100000000000000000000 1
b111000000000000000000000 *
b0 .
b100000000000000000000000 0
b1011000000000000000000000 +
b111000000000000000000000 /
b1000000010000000000000000000000 !
b1000000010000000000000000000000 3
b1000000111000000000000000000000 (
b1000000111000000000000000000000 2
1$
#40000
b1000000111100000000000000000000 1
b111100000000000000000000 +
b100000000000000000000 0
b11 .
0$
b111111000000000000000000000000 '
b111111000000000000000000000000 #
b111111000000000000000000000000 &
b1000000010000000000000000000000 4
#45000
b1000001000000000000000000000000 1
b1000000000000000000000000 +
b111100000000000000000000 /
b111100000000000000000000 *
b1000000111000000000000000000000 !
b1000000111000000000000000000000 3
b1000000111100000000000000000000 (
b1000000111100000000000000000000 2
1$
#50000
b111111000000000000000000000000 1
b0 *
b1111110 .
b100000000000000000000000 0
b100000000000000000000000 +
b0 /
b1111110 -
b0 !
b0 3
b0 (
b0 2
0$
1%
b1000000111000000000000000000000 4
#55000
1$
#60000
0$
b0 4
