code/e18-verilog-tb/src/clock_gating.v
module clock_gating (
    input en_w, en_r, clk,                  // signals that control the gated clock
    output wire write_clock,    // gated write clock
    output wire read_clock
);
    wire write;                        //to store the output of the and
    and(write, en_w, clk);               // create gated clock

    wire read;
    and(read, en_r, clk);

    assign write_clock = write;
    assign read_clock = read;
endmodule

code/e18-verilog-tb/src/clock_gating_tb.v
`timescale 1ns/100ps

module clock_gating_tb;

    reg en_w, en_r, clk;
    wire write_clock, read_clock;

    clock_gating test(en_w, en_r, clk, write_clock, read_clock);

    initial begin
        clk = 0;
        $dumpfile("clock_gating.vcd");
        $dumpvars(0, clock_gating_tb);
        #300000
        $finish;
    end

    // 1024 read -> calc -> 1024 write
    // when calculating, clock can go low

    // enable high- 2048 CC
    // enable low- 100 CC 

    // Generate the clock
    always #4 clk = ~clk;
    
    // toggle enable read signal
    initial begin
        forever begin
            en_r = 1;
            repeat (1024) @(posedge clk);
            en_r = 0;
            repeat (1124) @(posedge clk);
        end
    end

    // toggle enable write signal
    initial begin
        forever begin
            en_w = 0;
            repeat (1124) @(posedge clk);
            en_w = 1;
            repeat (1024) @(posedge clk);
        end
    end

endmodule

code/e18-verilog-tb/src/clock_gating.vcd
$date
	Thu May  1 13:39:01 2025
$end
$version
	Icarus Verilog
$end
$timescale
	100ps
$end
$scope module clock_gating_tb $end
$var wire 1 ! write_clock $end
$var wire 1 " read_clock $end
$var reg 1 # clk $end
$var reg 1 $ en_r $end
$var reg 1 % en_w $end
$scope module test $end
$var wire 1 # clk $end
$var wire 1 $ en_r $end
$var wire 1 % en_w $end
$var wire 1 & read $end
$var wire 1 " read_clock $end
$var wire 1 ' write $end
$var wire 1 ! write_clock $end
$upscope $end
$upscope $end
$enddefinitions $end
$comment Show the parameter values. $end
$dumpall
$end
#0
$dumpvars
0'
0&
0%
1$
0#
0"
0!
$end
#40
1"
1&
1#
#80
0"
0&
0#
#120
1"
1&
1#
#160
0"
0&
0#
#200
1"
1&
1#
#240
0"
0&
0#
#280
1"
1&
1#
#320
0"
0&
0#
#360
1"
1&
1#
#400
0"
0&
0#
#440
1"
1&
1#
#480
0"
0&
0#
#520
1"
1&
1#
#560
0"
0&
0#
#600
1"
1&
1#
#640
0"
0&
0#
#680
1"
1&
1#
#720
0"
0&
0#
#760
1"
1&
1#
#800
0"
0&
0#
#840
1"
1&
1#
#880
0"
0&
0#
#920
1"
1&
1#
#960
0"
0&
0#
#1000
1"
1&
1#
#1040
0"
0&
0#
#1080
1"
1&
1#
#1120
0"
0&
0#
#1160
1"
1&
1#
#1200
0"
0&
0#
#1240
1"
1&
1#
#1280
0"
0&
0#
#1320
1"
1&
1#
#1360
0"
0&
0#
#1400
1"
1&
1#
#1440
0"
0&
0#
#1480
1"
1&
1#
#1520
0"
0&
0#
#1560
1"
1&
1#
#1600
0"
0&
0#
#1640
1"
1&
1#
#1680
0"
0&
0#
#1720
1"
1&
1#
#1760
0"
0&
0#
#1800
1"
1&
1#
#1840
0"
0&
0#
#1880
1"
1&
1#
#1920
0"
0&
0#
#1960
1"
1&
1#
#2000
0"
0&
0#
#2040
1"
1&
1#
#2080
0"
0&
0#
#2120
1"
1&
1#
#2160
0"
0&
0#
#2200
1"
1&
1#
#2240
0"
0&
0#
#2280
1"
1&
1#
#2320
0"
0&
0#
#2360
1"
1&
1#
#2400
0"
0&
0#
#2440
1"
1&
1#
#2480
0"
0&
0#
#2520
1"
1&
1#
#2560
0"
0&
0#
#2600
1"
1&
1#
#2640
0"
0&
0#
#2680
1"
1&
1#
#2720
0"
0&
0#
#2760
1"
1&
1#
#2800
0"
0&
0#
#2840
1"
1&
1#
#2880
0"
0&
0#
#2920
1"
1&
1#
#2960
0"
0&
0#
#3000
1"
1&
1#
#3040
0"
0&
0#
#3080
1"
1&
1#
#3120
0"
0&
0#
#3160
1"
1&
1#
#3200
0"
0&
0#
#3240
1"
1&
1#
#3280
0"
0&
0#
#3320
1"
1&
1#
#3360
0"
0&
0#
#3400
1"
1&
1#
#3440
0"
0&
0#
#3480
1"
1&
1#
#3520
0"
0&
0#
#3560
1"
1&
1#
#3600
0"
0&
0#
#3640
1"
1&
1#
#3680
0"
0&
0#
#3720
1"
1&
1#
#3760
0"
0&
0#
#3800
1"
1&
1#
#3840
0"
0&
0#
#3880
1"
1&
1#
#3920
0"
0&
0#
#3960
1"
1&
1#
#4000
0"
0&
0#
#4040
1"
1&
1#
#4080
0"
0&
0#
#4120
1"
1&
1#
#4160
0"
0&
0#
#4200
1"
1&
1#
#4240
0"
0&
0#
#4280
1"
1&
1#
#4320
0"
0&
0#
#4360
1"
1&
1#
#4400
0"
0&
0#
#4440
1"
1&
1#
#4480
0"
0&
0#
#4520
1"
1&
1#
#4560
0"
0&
0#
#4600
1"
1&
1#
#4640
0"
0&
0#
#4680
1"
1&
1#
#4720
0"
0&
0#
#4760
1"
1&
1#
#4800
0"
0&
0#
#4840
1"
1&
1#
#4880
0"
0&
0#
#4920
1"
1&
1#
#4960
0"
0&
0#
#5000
1"
1&
1#
#5040
0"
0&
0#
#5080
1"
1&
1#
#5120
0"
0&
0#
#5160
1"
1&
1#
#5200
0"
0&
0#
#5240
1"
1&
1#
#5280
0"
0&
0#
#5320
1"
1&
1#
#5360
0"
0&
0#
#5400
1"
1&
1#
#5440
0"
0&
0#
#5480
1"
1&
1#
#5520
0"
0&
0#
#5560
1"
1&
1#
#5600
0"
0&
0#
#5640
1"
1&
1#
#5680
0"
0&
0#
#5720
1"
1&
1#
#5760
0"
0&
0#
#5800
1"
1&
1#
#5840
0"
0&
0#
#5880
1"
1&
1#
#5920
0"
0&
0#
#5960
1"
1&
1#
#6000
0"
0&
0#
#6040
1"
1&
1#
#6080
0"
0&
0#
#6120
1"
1&
1#
#6160
0"
0&
0#
#6200
1"
1&
1#
#6240
0"
0&
0#
#6280
1"
1&
1#
#6320
0"
0&
0#
#6360
1"
1&
1#
#6400
0"
0&
0#
#6440
1"
1&
1#
#6480
0"
0&
0#
#6520
1"
1&
1#
#6560
0"
0&
0#
#6600
1"
1&
1#
#6640
0"
0&
0#
#6680
1"
1&
1#
#6720
0"
0&
0#
#6760
1"
1&
1#
#6800
0"
0&
0#
#6840
1"
1&
1#
#6880
0"
0&
0#
#6920
1"
1&
1#
#6960
0"
0&
0#
#7000
1"
1&
1#
#7040
0"
0&
0#
#7080
1"
1&
1#
#7120
0"
0&
0#
#7160
1"
1&
1#
#7200
0"
0&
0#
#7240
1"
1&
1#
#7280
0"
0&
0#
#7320
1"
1&
1#
#7360
0"
0&
0#
#7400
1"
1&
1#
#7440
0"
0&
0#
#7480
1"
1&
1#
#7520
0"
0&
0#
#7560
1"
1&
1#
#7600
0"
0&
0#
#7640
1"
1&
1#
#7680
0"
0&
0#
#7720
1"
1&
1#
#7760
0"
0&
0#
#7800
1"
1&
1#
#7840
0"
0&
0#
#7880
1"
1&
1#
#7920
0"
0&
0#
#7960
1"
1&
1#
#8000
0"
0&
0#
#8040
1"
1&
1#
#8080
0"
0&
0#
#8120
1"
1&
1#
#8160
0"
0&
0#
#8200
1"
1&
1#
#8240
0"
0&
0#
#8280
1"
1&
1#
#8320
0"
0&
0#
#8360
1"
1&
1#
#8400
0"
0&
0#
#8440
1"
1&
1#
#8480
0"
0&
0#
#8520
1"
1&
1#
#8560
0"
0&
0#
#8600
1"
1&
1#
#8640
0"
0&
0#
#8680
1"
1&
1#
#8720
0"
0&
0#
#8760
1"
1&
1#
#8800
0"
0&
0#
#8840
1"
1&
1#
#8880
0"
0&
0#
#8920
1"
1&
1#
#8960
0"
0&
0#
#9000
1"
1&
1#
#9040
0"
0&
0#
#9080
1"
1&
1#
#9120
0"
0&
0#
#9160
1"
1&
1#
#9200
0"
0&
0#
#9240
1"
1&
1#
#9280
0"
0&
0#
#9320
1"
1&
1#
#9360
0"
0&
0#
#9400
1"
1&
1#
#9440
0"
0&
0#
#9480
1"
1&
1#
#9520
0"
0&
0#
#9560
1"
1&
1#
#9600
0"
0&
0#
#9640
1"
1&
1#
#9680
0"
0&
0#
#9720
1"
1&
1#
#9760
0"
0&
0#
#9800
1"
1&
1#
#9840
0"
0&
0#
#9880
1"
1&
1#
#9920
0"
0&
0#
#9960
1"
1&
1#
#10000
0"
0&
0#
#10040
1"
1&
1#
#10080
0"
0&
0#
#10120
1"
1&
1#
#10160
0"
0&
0#
#10200
1"
1&
1#
#10240
0"
0&
0#
#10280
1"
1&
1#
#10320
0"
0&
0#
#10360
1"
1&
1#
#10400
0"
0&
0#
#10440
1"
1&
1#
#10480
0"
0&
0#
#10520
1"
1&
1#
#10560
0"
0&
0#
#10600
1"
1&
1#
#10640
0"
0&
0#
#10680
1"
1&
1#
#10720
0"
0&
0#
#10760
1"
1&
1#
#10800
0"
0&
0#
#10840
1"
1&
1#
#10880
0"
0&
0#
#10920
1"
1&
1#
#10960
0"
0&
0#
#11000
1"
1&
1#
#11040
0"
0&
0#
#11080
1"
1&
1#
#11120
0"
0&
0#
#11160
1"
1&
1#
#11200
0"
0&
0#
#11240
1"
1&
1#
#11280
0"
0&
0#
#11320
1"
1&
1#
#11360
0"
0&
0#
#11400
1"
1&
1#
#11440
0"
0&
0#
#11480
1"
1&
1#
#11520
0"
0&
0#
#11560
1"
1&
1#
#11600
0"
0&
0#
#11640
1"
1&
1#
#11680
0"
0&
0#
#11720
1"
1&
1#
#11760
0"
0&
0#
#11800
1"
1&
1#
#11840
0"
0&
0#
#11880
1"
1&
1#
#11920
0"
0&
0#
#11960
1"
1&
1#
#12000
0"
0&
0#
#12040
1"
1&
1#
#12080
0"
0&
0#
#12120
1"
1&
1#
#12160
0"
0&
0#
#12200
1"
1&
1#
#12240
0"
0&
0#
#12280
1"
1&
1#
#12320
0"
0&
0#
#12360
1"
1&
1#
#12400
0"
0&
0#
#12440
1"
1&
1#
#12480
0"
0&
0#
#12520
1"
1&
1#
#12560
0"
0&
0#
#12600
1"
1&
1#
#12640
0"
0&
0#
#12680
1"
1&
1#
#12720
0"
0&
0#
#12760
1"
1&
1#
#12800
0"
0&
0#
#12840
1"
1&
1#
#12880
0"
0&
0#
#12920
1"
1&
1#
#12960
0"
0&
0#
#13000
1"
1&
1#
#13040
0"
0&
0#
#13080
1"
1&
1#
#13120
0"
0&
0#
#13160
1"
1&
1#
#13200
0"
0&
0#
#13240
1"
1&
1#
#13280
0"
0&
0#
#13320
1"
1&
1#
#13360
0"
0&
0#
#13400
1"
1&
1#
#13440
0"
0&
0#
#13480
1"
1&
1#
#13520
0"
0&
0#
#13560
1"
1&
1#
#13600
0"
0&
0#
#13640
1"
1&
1#
#13680
0"
0&
0#
#13720
1"
1&
1#
#13760
0"
0&
0#
#13800
1"
1&
1#
#13840
0"
0&
0#
#13880
1"
1&
1#
#13920
0"
0&
0#
#13960
1"
1&
1#
#14000
0"
0&
0#
#14040
1"
1&
1#
#14080
0"
0&
0#
#14120
1"
1&
1#
#14160
0"
0&
0#
#14200
1"
1&
1#
#14240
0"
0&
0#
#14280
1"
1&
1#
#14320
0"
0&
0#
#14360
1"
1&
1#
#14400
0"
0&
0#
#14440
1"
1&
1#
#14480
0"
0&
0#
#14520
1"
1&
1#
#14560
0"
0&
0#
#14600
1"
1&
1#
#14640
0"
0&
0#
#14680
1"
1&
1#
#14720
0"
0&
0#
#14760
1"
1&
1#
#14800
0"
0&
0#
#14840
1"
1&
1#
#14880
0"
0&
0#
#14920
1"
1&
1#
#14960
0"
0&
0#
#15000
1"
1&
1#
#15040
0"
0&
0#
#15080
1"
1&
1#
#15120
0"
0&
0#
#15160
1"
1&
1#
#15200
0"
0&
0#
#15240
1"
1&
1#
#15280
0"
0&
0#
#15320
1"
1&
1#
#15360
0"
0&
0#
#15400
1"
1&
1#
#15440
0"
0&
0#
#15480
1"
1&
1#
#15520
0"
0&
0#
#15560
1"
1&
1#
#15600
0"
0&
0#
#15640
1"
1&
1#
#15680
0"
0&
0#
#15720
1"
1&
1#
#15760
0"
0&
0#
#15800
1"
1&
1#
#15840
0"
0&
0#
#15880
1"
1&
1#
#15920
0"
0&
0#
#15960
1"
1&
1#
#16000
0"
0&
0#
#16040
1"
1&
1#
#16080
0"
0&
0#
#16120
1"
1&
1#
#16160
0"
0&
0#
#16200
1"
1&
1#
#16240
0"
0&
0#
#16280
1"
1&
1#
#16320
0"
0&
0#
#16360
1"
1&
1#
#16400
0"
0&
0#
#16440
1"
1&
1#
#16480
0"
0&
0#
#16520
1"
1&
1#
#16560
0"
0&
0#
#16600
1"
1&
1#
#16640
0"
0&
0#
#16680
1"
1&
1#
#16720
0"
0&
0#
#16760
1"
1&
1#
#16800
0"
0&
0#
#16840
1"
1&
1#
#16880
0"
0&
0#
#16920
1"
1&
1#
#16960
0"
0&
0#
#17000
1"
1&
1#
#17040
0"
0&
0#
#17080
1"
1&
1#
#17120
0"
0&
0#
#17160
1"
1&
1#
#17200
0"
0&
0#
#17240
1"
1&
1#
#17280
0"
0&
0#
#17320
1"
1&
1#
#17360
0"
0&
0#
#17400
1"
1&
1#
#17440
0"
0&
0#
#17480
1"
1&
1#
#17520
0"
0&
0#
#17560
1"
1&
1#
#17600
0"
0&
0#
#17640
1"
1&
1#
#17680
0"
0&
0#
#17720
1"
1&
1#
#17760
0"
0&
0#
#17800
1"
1&
1#
#17840
0"
0&
0#
#17880
1"
1&
1#
#17920
0"
0&
0#
#17960
1"
1&
1#
#18000
0"
0&
0#
#18040
1"
1&
1#
#18080
0"
0&
0#
#18120
1"
1&
1#
#18160
0"
0&
0#
#18200
1"
1&
1#
#18240
0"
0&
0#
#18280
1"
1&
1#
#18320
0"
0&
0#
#18360
1"
1&
1#
#18400
0"
0&
0#
#18440
1"
1&
1#
#18480
0"
0&
0#
#18520
1"
1&
1#
#18560
0"
0&
0#
#18600
1"
1&
1#
#18640
0"
0&
0#
#18680
1"
1&
1#
#18720
0"
0&
0#
#18760
1"
1&
1#
#18800
0"
0&
0#
#18840
1"
1&
1#
#18880
0"
0&
0#
#18920
1"
1&
1#
#18960
0"
0&
0#
#19000
1"
1&
1#
#19040
0"
0&
0#
#19080
1"
1&
1#
#19120
0"
0&
0#
#19160
1"
1&
1#
#19200
0"
0&
0#
#19240
1"
1&
1#
#19280
0"
0&
0#
#19320
1"
1&
1#
#19360
0"
0&
0#
#19400
1"
1&
1#
#19440
0"
0&
0#
#19480
1"
1&
1#
#19520
0"
0&
0#
#19560
1"
1&
1#
#19600
0"
0&
0#
#19640
1"
1&
1#
#19680
0"
0&
0#
#19720
1"
1&
1#
#19760
0"
0&
0#
#19800
1"
1&
1#
#19840
0"
0&
0#
#19880
1"
1&
1#
#19920
0"
0&
0#
#19960
1"
1&
1#
#20000
0"
0&
0#
#20040
1"
1&
1#
#20080
0"
0&
0#
#20120
1"
1&
1#
#20160
0"
0&
0#
#20200
1"
1&
1#
#20240
0"
0&
0#
#20280
1"
1&
1#
#20320
0"
0&
0#
#20360
1"
1&
1#
#20400
0"
0&
0#
#20440
1"
1&
1#
#20480
0"
0&
0#
#20520
1"
1&
1#
#20560
0"
0&
0#
#20600
1"
1&
1#
#20640
0"
0&
0#
#20680
1"
1&
1#
#20720
0"
0&
0#
#20760
1"
1&
1#
#20800
0"
0&
0#
#20840
1"
1&
1#
#20880
0"
0&
0#
#20920
1"
1&
1#
#20960
0"
0&
0#
#21000
1"
1&
1#
#21040
0"
0&
0#
#21080
1"
1&
1#
#21120
0"
0&
0#
#21160
1"
1&
1#
#21200
0"
0&
0#
#21240
1"
1&
1#
#21280
0"
0&
0#
#21320
1"
1&
1#
#21360
0"
0&
0#
#21400
1"
1&
1#
#21440
0"
0&
0#
#21480
1"
1&
1#
#21520
0"
0&
0#
#21560
1"
1&
1#
#21600
0"
0&
0#
#21640
1"
1&
1#
#21680
0"
0&
0#
#21720
1"
1&
1#
#21760
0"
0&
0#
#21800
1"
1&
1#
#21840
0"
0&
0#
#21880
1"
1&
1#
#21920
0"
0&
0#
#21960
1"
1&
1#
#22000
0"
0&
0#
#22040
1"
1&
1#
#22080
0"
0&
0#
#22120
1"
1&
1#
#22160
0"
0&
0#
#22200
1"
1&
1#
#22240
0"
0&
0#
#22280
1"
1&
1#
#22320
0"
0&
0#
#22360
1"
1&
1#
#22400
0"
0&
0#
#22440
1"
1&
1#
#22480
0"
0&
0#
#22520
1"
1&
1#
#22560
0"
0&
0#
#22600
1"
1&
1#
#22640
0"
0&
0#
#22680
1"
1&
1#
#22720
0"
0&
0#
#22760
1"
1&
1#
#22800
0"
0&
0#
#22840
1"
1&
1#
#22880
0"
0&
0#
#22920
1"
1&
1#
#22960
0"
0&
0#
#23000
1"
1&
1#
#23040
0"
0&
0#
#23080
1"
1&
1#
#23120
0"
0&
0#
#23160
1"
1&
1#
#23200
0"
0&
0#
#23240
1"
1&
1#
#23280
0"
0&
0#
#23320
1"
1&
1#
#23360
0"
0&
0#
#23400
1"
1&
1#
#23440
0"
0&
0#
#23480
1"
1&
1#
#23520
0"
0&
0#
#23560
1"
1&
1#
#23600
0"
0&
0#
#23640
1"
1&
1#
#23680
0"
0&
0#
#23720
1"
1&
1#
#23760
0"
0&
0#
#23800
1"
1&
1#
#23840
0"
0&
0#
#23880
1"
1&
1#
#23920
0"
0&
0#
#23960
1"
1&
1#
#24000
0"
0&
0#
#24040
1"
1&
1#
#24080
0"
0&
0#
#24120
1"
1&
1#
#24160
0"
0&
0#
#24200
1"
1&
1#
#24240
0"
0&
0#
#24280
1"
1&
1#
#24320
0"
0&
0#
#24360
1"
1&
1#
#24400
0"
0&
0#
#24440
1"
1&
1#
#24480
0"
0&
0#
#24520
1"
1&
1#
#24560
0"
0&
0#
#24600
1"
1&
1#
#24640
0"
0&
0#
#24680
1"
1&
1#
#24720
0"
0&
0#
#24760
1"
1&
1#
#24800
0"
0&
0#
#24840
1"
1&
1#
#24880
0"
0&
0#
#24920
1"
1&
1#
#24960
0"
0&
0#
#25000
1"
1&
1#
#25040
0"
0&
0#
#25080
1"
1&
1#
#25120
0"
0&
0#
#25160
1"
1&
1#
#25200
0"
0&
0#
#25240
1"
1&
1#
#25280
0"
0&
0#
#25320
1"
1&
1#
#25360
0"
0&
0#
#25400
1"
1&
1#
#25440
0"
0&
0#
#25480
1"
1&
1#
#25520
0"
0&
0#
#25560
1"
1&
1#
#25600
0"
0&
0#
#25640
1"
1&
1#
#25680
0"
0&
0#
#25720
1"
1&
1#
#25760
0"
0&
0#
#25800
1"
1&
1#
#25840
0"
0&
0#
#25880
1"
1&
1#
#25920
0"
0&
0#
#25960
1"
1&
1#
#26000
0"
0&
0#
#26040
1"
1&
1#
#26080
0"
0&
0#
#26120
1"
1&
1#
#26160
0"
0&
0#
#26200
1"
1&
1#
#26240
0"
0&
0#
#26280
1"
1&
1#
#26320
0"
0&
0#
#26360
1"
1&
1#
#26400
0"
0&
0#
#26440
1"
1&
1#
#26480
0"
0&
0#
#26520
1"
1&
1#
#26560
0"
0&
0#
#26600
1"
1&
1#
#26640
0"
0&
0#
#26680
1"
1&
1#
#26720
0"
0&
0#
#26760
1"
1&
1#
#26800
0"
0&
0#
#26840
1"
1&
1#
#26880
0"
0&
0#
#26920
1"
1&
1#
#26960
0"
0&
0#
#27000
1"
1&
1#
#27040
0"
0&
0#
#27080
1"
1&
1#
#27120
0"
0&
0#
#27160
1"
1&
1#
#27200
0"
0&
0#
#27240
1"
1&
1#
#27280
0"
0&
0#
#27320
1"
1&
1#
#27360
0"
0&
0#
#27400
1"
1&
1#
#27440
0"
0&
0#
#27480
1"
1&
1#
#27520
0"
0&
0#
#27560
1"
1&
1#
#27600
0"
0&
0#
#27640
1"
1&
1#
#27680
0"
0&
0#
#27720
1"
1&
1#
#27760
0"
0&
0#
#27800
1"
1&
1#
#27840
0"
0&
0#
#27880
1"
1&
1#
#27920
0"
0&
0#
#27960
1"
1&
1#
#28000
0"
0&
0#
#28040
1"
1&
1#
#28080
0"
0&
0#
#28120
1"
1&
1#
#28160
0"
0&
0#
#28200
1"
1&
1#
#28240
0"
0&
0#
#28280
1"
1&
1#
#28320
0"
0&
0#
#28360
1"
1&
1#
#28400
0"
0&
0#
#28440
1"
1&
1#
#28480
0"
0&
0#
#28520
1"
1&
1#
#28560
0"
0&
0#
#28600
1"
1&
1#
#28640
0"
0&
0#
#28680
1"
1&
1#
#28720
0"
0&
0#
#28760
1"
1&
1#
#28800
0"
0&
0#
#28840
1"
1&
1#
#28880
0"
0&
0#
#28920
1"
1&
1#
#28960
0"
0&
0#
#29000
1"
1&
1#
#29040
0"
0&
0#
#29080
1"
1&
1#
#29120
0"
0&
0#
#29160
1"
1&
1#
#29200
0"
0&
0#
#29240
1"
1&
1#
#29280
0"
0&
0#
#29320
1"
1&
1#
#29360
0"
0&
0#
#29400
1"
1&
1#
#29440
0"
0&
0#
#29480
1"
1&
1#
#29520
0"
0&
0#
#29560
1"
1&
1#
#29600
0"
0&
0#
#29640
1"
1&
1#
#29680
0"
0&
0#
#29720
1"
1&
1#
#29760
0"
0&
0#
#29800
1"
1&
1#
#29840
0"
0&
0#
#29880
1"
1&
1#
#29920
0"
0&
0#
#29960
1"
1&
1#
#30000
0"
0&
0#
#30040
1"
1&
1#
#30080
0"
0&
0#
#30120
1"
1&
1#
#30160
0"
0&
0#
#30200
1"
1&
1#
#30240
0"
0&
0#
#30280
1"
1&
1#
#30320
0"
0&
0#
#30360
1"
1&
1#
#30400
0"
0&
0#
#30440
1"
1&
1#
#30480
0"
0&
0#
#30520
1"
1&
1#
#30560
0"
0&
0#
#30600
1"
1&
1#
#30640
0"
0&
0#
#30680
1"
1&
1#
#30720
0"
0&
0#
#30760
1"
1&
1#
#30800
0"
0&
0#
#30840
1"
1&
1#
#30880
0"
0&
0#
#30920
1"
1&
1#
#30960
0"
0&
0#
#31000
1"
1&
1#
#31040
0"
0&
0#
#31080
1"
1&
1#
#31120
0"
0&
0#
#31160
1"
1&
1#
#31200
0"
0&
0#
#31240
1"
1&
1#
#31280
0"
0&
0#
#31320
1"
1&
1#
#31360
0"
0&
0#
#31400
1"
1&
1#
#31440
0"
0&
0#
#31480
1"
1&
1#
#31520
0"
0&
0#
#31560
1"
1&
1#
#31600
0"
0&
0#
#31640
1"
1&
1#
#31680
0"
0&
0#
#31720
1"
1&
1#
#31760
0"
0&
0#
#31800
1"
1&
1#
#31840
0"
0&
0#
#31880
1"
1&
1#
#31920
0"
0&
0#
#31960
1"
1&
1#
#32000
0"
0&
0#
#32040
1"
1&
1#
#32080
0"
0&
0#
#32120
1"
1&
1#
#32160
0"
0&
0#
#32200
1"
1&
1#
#32240
0"
0&
0#
#32280
1"
1&
1#
#32320
0"
0&
0#
#32360
1"
1&
1#
#32400
0"
0&
0#
#32440
1"
1&
1#
#32480
0"
0&
0#
#32520
1"
1&
1#
#32560
0"
0&
0#
#32600
1"
1&
1#
#32640
0"
0&
0#
#32680
1"
1&
1#
#32720
0"
0&
0#
#32760
1"
1&
1#
#32800
0"
0&
0#
#32840
1"
1&
1#
#32880
0"
0&
0#
#32920
1"
1&
1#
#32960
0"
0&
0#
#33000
1"
1&
1#
#33040
0"
0&
0#
#33080
1"
1&
1#
#33120
0"
0&
0#
#33160
1"
1&
1#
#33200
0"
0&
0#
#33240
1"
1&
1#
#33280
0"
0&
0#
#33320
1"
1&
1#
#33360
0"
0&
0#
#33400
1"
1&
1#
#33440
0"
0&
0#
#33480
1"
1&
1#
#33520
0"
0&
0#
#33560
1"
1&
1#
#33600
0"
0&
0#
#33640
1"
1&
1#
#33680
0"
0&
0#
#33720
1"
1&
1#
#33760
0"
0&
0#
#33800
1"
1&
1#
#33840
0"
0&
0#
#33880
1"
1&
1#
#33920
0"
0&
0#
#33960
1"
1&
1#
#34000
0"
0&
0#
#34040
1"
1&
1#
#34080
0"
0&
0#
#34120
1"
1&
1#
#34160
0"
0&
0#
#34200
1"
1&
1#
#34240
0"
0&
0#
#34280
1"
1&
1#
#34320
0"
0&
0#
#34360
1"
1&
1#
#34400
0"
0&
0#
#34440
1"
1&
1#
#34480
0"
0&
0#
#34520
1"
1&
1#
#34560
0"
0&
0#
#34600
1"
1&
1#
#34640
0"
0&
0#
#34680
1"
1&
1#
#34720
0"
0&
0#
#34760
1"
1&
1#
#34800
0"
0&
0#
#34840
1"
1&
1#
#34880
0"
0&
0#
#34920
1"
1&
1#
#34960
0"
0&
0#
#35000
1"
1&
1#
#35040
0"
0&
0#
#35080
1"
1&
1#
#35120
0"
0&
0#
#35160
1"
1&
1#
#35200
0"
0&
0#
#35240
1"
1&
1#
#35280
0"
0&
0#
#35320
1"
1&
1#
#35360
0"
0&
0#
#35400
1"
1&
1#
#35440
0"
0&
0#
#35480
1"
1&
1#
#35520
0"
0&
0#
#35560
1"
1&
1#
#35600
0"
0&
0#
#35640
1"
1&
1#
#35680
0"
0&
0#
#35720
1"
1&
1#
#35760
0"
0&
0#
#35800
1"
1&
1#
#35840
0"
0&
0#
#35880
1"
1&
1#
#35920
0"
0&
0#
#35960
1"
1&
1#
#36000
0"
0&
0#
#36040
1"
1&
1#
#36080
0"
0&
0#
#36120
1"
1&
1#
#36160
0"
0&
0#
#36200
1"
1&
1#
#36240
0"
0&
0#
#36280
1"
1&
1#
#36320
0"
0&
0#
#36360
1"
1&
1#
#36400
0"
0&
0#
#36440
1"
1&
1#
#36480
0"
0&
0#
#36520
1"
1&
1#
#36560
0"
0&
0#
#36600
1"
1&
1#
#36640
0"
0&
0#
#36680
1"
1&
1#
#36720
0"
0&
0#
#36760
1"
1&
1#
#36800
0"
0&
0#
#36840
1"
1&
1#
#36880
0"
0&
0#
#36920
1"
1&
1#
#36960
0"
0&
0#
#37000
1"
1&
1#
#37040
0"
0&
0#
#37080
1"
1&
1#
#37120
0"
0&
0#
#37160
1"
1&
1#
#37200
0"
0&
0#
#37240
1"
1&
1#
#37280
0"
0&
0#
#37320
1"
1&
1#
#37360
0"
0&
0#
#37400
1"
1&
1#
#37440
0"
0&
0#
#37480
1"
1&
1#
#37520
0"
0&
0#
#37560
1"
1&
1#
#37600
0"
0&
0#
#37640
1"
1&
1#
#37680
0"
0&
0#
#37720
1"
1&
1#
#37760
0"
0&
0#
#37800
1"
1&
1#
#37840
0"
0&
0#
#37880
1"
1&
1#
#37920
0"
0&
0#
#37960
1"
1&
1#
#38000
0"
0&
0#
#38040
1"
1&
1#
#38080
0"
0&
0#
#38120
1"
1&
1#
#38160
0"
0&
0#
#38200
1"
1&
1#
#38240
0"
0&
0#
#38280
1"
1&
1#
#38320
0"
0&
0#
#38360
1"
1&
1#
#38400
0"
0&
0#
#38440
1"
1&
1#
#38480
0"
0&
0#
#38520
1"
1&
1#
#38560
0"
0&
0#
#38600
1"
1&
1#
#38640
0"
0&
0#
#38680
1"
1&
1#
#38720
0"
0&
0#
#38760
1"
1&
1#
#38800
0"
0&
0#
#38840
1"
1&
1#
#38880
0"
0&
0#
#38920
1"
1&
1#
#38960
0"
0&
0#
#39000
1"
1&
1#
#39040
0"
0&
0#
#39080
1"
1&
1#
#39120
0"
0&
0#
#39160
1"
1&
1#
#39200
0"
0&
0#
#39240
1"
1&
1#
#39280
0"
0&
0#
#39320
1"
1&
1#
#39360
0"
0&
0#
#39400
1"
1&
1#
#39440
0"
0&
0#
#39480
1"
1&
1#
#39520
0"
0&
0#
#39560
1"
1&
1#
#39600
0"
0&
0#
#39640
1"
1&
1#
#39680
0"
0&
0#
#39720
1"
1&
1#
#39760
0"
0&
0#
#39800
1"
1&
1#
#39840
0"
0&
0#
#39880
1"
1&
1#
#39920
0"
0&
0#
#39960
1"
1&
1#
#40000
0"
0&
0#
#40040
1"
1&
1#
#40080
0"
0&
0#
#40120
1"
1&
1#
#40160
0"
0&
0#
#40200
1"
1&
1#
#40240
0"
0&
0#
#40280
1"
1&
1#
#40320
0"
0&
0#
#40360
1"
1&
1#
#40400
0"
0&
0#
#40440
1"
1&
1#
#40480
0"
0&
0#
#40520
1"
1&
1#
#40560
0"
0&
0#
#40600
1"
1&
1#
#40640
0"
0&
0#
#40680
1"
1&
1#
#40720
0"
0&
0#
#40760
1"
1&
1#
#40800
0"
0&
0#
#40840
1"
1&
1#
#40880
0"
0&
0#
#40920
1"
1&
1#
#40960
0"
0&
0#
#41000
1"
1&
1#
#41040
0"
0&
0#
#41080
1"
1&
1#
#41120
0"
0&
0#
#41160
1"
1&
1#
#41200
0"
0&
0#
#41240
1"
1&
1#
#41280
0"
0&
0#
#41320
1"
1&
1#
#41360
0"
0&
0#
#41400
1"
1&
1#
#41440
0"
0&
0#
#41480
1"
1&
1#
#41520
0"
0&
0#
#41560
1"
1&
1#
#41600
0"
0&
0#
#41640
1"
1&
1#
#41680
0"
0&
0#
#41720
1"
1&
1#
#41760
0"
0&
0#
#41800
1"
1&
1#
#41840
0"
0&
0#
#41880
1"
1&
1#
#41920
0"
0&
0#
#41960
1"
1&
1#
#42000
0"
0&
0#
#42040
1"
1&
1#
#42080
0"
0&
0#
#42120
1"
1&
1#
#42160
0"
0&
0#
#42200
1"
1&
1#
#42240
0"
0&
0#
#42280
1"
1&
1#
#42320
0"
0&
0#
#42360
1"
1&
1#
#42400
0"
0&
0#
#42440
1"
1&
1#
#42480
0"
0&
0#
#42520
1"
1&
1#
#42560
0"
0&
0#
#42600
1"
1&
1#
#42640
0"
0&
0#
#42680
1"
1&
1#
#42720
0"
0&
0#
#42760
1"
1&
1#
#42800
0"
0&
0#
#42840
1"
1&
1#
#42880
0"
0&
0#
#42920
1"
1&
1#
#42960
0"
0&
0#
#43000
1"
1&
1#
#43040
0"
0&
0#
#43080
1"
1&
1#
#43120
0"
0&
0#
#43160
1"
1&
1#
#43200
0"
0&
0#
#43240
1"
1&
1#
#43280
0"
0&
0#
#43320
1"
1&
1#
