code/e18-verilog-tb/src/Priority_Encoder.v
////////////////////////////////////////////////////////////////////////////////////////////////////////////////////
//File Name: Priority Encoder.v
//Created By: Sheetal Swaroop Burada
//Date: 30-04-2019
//Project Name: Design of 32 Bit Floating Point ALU Based on Standard IEEE-754 in Verilog and its implementation on FPGA.
//University: Dayalbagh Educational Institute
////////////////////////////////////////////////////////////////////////////////////////////////////////////////////
`timescale 1ns/100ps

module priority_encoder(
			input [24:0] significand,
			input [7:0] Exponent_a,
			output reg [24:0] Significand,
			output [7:0] Exponent_sub
			);

reg [4:0] shift;

always @(significand)
begin
	casex (significand)
		25'b1_1xxx_xxxx_xxxx_xxxx_xxxx_xxxx :	begin
													Significand = significand;
									 				shift = 5'd0;
								 			  	end
		25'b1_01xx_xxxx_xxxx_xxxx_xxxx_xxxx : 	begin						
										 			Significand = significand << 1;
									 				shift = 5'd1;
								 			  	end

		25'b1_001x_xxxx_xxxx_xxxx_xxxx_xxxx : 	begin						
										 			Significand = significand << 2;
									 				shift = 5'd2;
								 				end

		25'b1_0001_xxxx_xxxx_xxxx_xxxx_xxxx : 	begin 							
													Significand = significand << 3;
								 	 				shift = 5'd3;
								 				end

		25'b1_0000_1xxx_xxxx_xxxx_xxxx_xxxx : 	begin						
									 				Significand = significand << 4;
								 	 				shift = 5'd4;
								 				end

		25'b1_0000_01xx_xxxx_xxxx_xxxx_xxxx : 	begin						
									 				Significand = significand << 5;
								 	 				shift = 5'd5;
								 				end

		25'b1_0000_001x_xxxx_xxxx_xxxx_xxxx : 	begin						// 24'h020000
									 				Significand = significand << 6;
								 	 				shift = 5'd6;
								 				end

		25'b1_0000_0001_xxxx_xxxx_xxxx_xxxx : 	begin						// 24'h010000
									 				Significand = significand << 7;
								 	 				shift = 5'd7;
								 				end

		25'b1_0000_0000_1xxx_xxxx_xxxx_xxxx : 	begin						// 24'h008000
									 				Significand = significand << 8;
								 	 				shift = 5'd8;
								 				end

		25'b1_0000_0000_01xx_xxxx_xxxx_xxxx : 	begin						// 24'h004000
									 				Significand = significand << 9;
								 	 				shift = 5'd9;
								 				end

		25'b1_0000_0000_001x_xxxx_xxxx_xxxx : 	begin						// 24'h002000
									 				Significand = significand << 10;
								 	 				shift = 5'd10;
								 				end

		25'b1_0000_0000_0001_xxxx_xxxx_xxxx : 	begin						// 24'h001000
									 				Significand = significand << 11;
								 	 				shift = 5'd11;
								 				end

		25'b1_0000_0000_0000_1xxx_xxxx_xxxx : 	begin						// 24'h000800
									 				Significand = significand << 12;
								 	 				shift = 5'd12;
								 				end

		25'b1_0000_0000_0000_01xx_xxxx_xxxx : 	begin						// 24'h000400
									 				Significand = significand << 13;
								 	 				shift = 5'd13;
								 				end

		25'b1_0000_0000_0000_001x_xxxx_xxxx : 	begin						// 24'h000200
									 				Significand = significand << 14;
								 	 				shift = 5'd14;
								 				end

		25'b1_0000_0000_0000_0001_xxxx_xxxx  : 	begin						// 24'h000100
									 				Significand = significand << 15;
								 	 				shift = 5'd15;
								 				end

		25'b1_0000_0000_0000_0000_1xxx_xxxx : 	begin						// 24'h000080
									 				Significand = significand << 16;
								 	 				shift = 5'd16;
								 				end

		25'b1_0000_0000_0000_0000_01xx_xxxx : 	begin						// 24'h000040
											 		Significand = significand << 17;
										 	 		shift = 5'd17;
												end

		25'b1_0000_0000_0000_0000_001x_xxxx : 	begin						// 24'h000020
									 				Significand = significand << 18;
								 	 				shift = 5'd18;
								 				end

		25'b1_0000_0000_0000_0000_0001_xxxx : 	begin						// 24'h000010
									 				Significand = significand << 19;
								 	 				shift = 5'd19;
												end

		25'b1_0000_0000_0000_0000_0000_1xxx :	begin						// 24'h000008
									 				Significand = significand << 20;
								 					shift = 5'd20;
								 				end

		25'b1_0000_0000_0000_0000_0000_01xx : 	begin						// 24'h000004
									 				Significand = significand << 21;
								 	 				shift = 5'd21;
								 				end

		25'b1_0000_0000_0000_0000_0000_001x : 	begin						// 24'h000002
									 				Significand = significand << 22;
								 	 				shift = 5'd22;
								 				end

		25'b1_0000_0000_0000_0000_0000_0001 : 	begin						// 24'h000001
									 				Significand = significand << 23;
								 	 				shift = 5'd23;
								 				end

		25'b1_0000_0000_0000_0000_0000_0000 : 	begin						// 24'h000000
								 					Significand = significand << 24;
							 	 					shift = 5'd24;
								 				end
		default : 	begin
						Significand = (~significand) + 1'b1;
						shift = 5'd0;
					end

	endcase
end
assign Exponent_sub = Exponent_a - shift;

endmodule

code/e18-verilog-tb/src/Addition_Subtraction.v
////////////////////////////////////////////////////////////////////////////////////////////////////////////////////
//File Name: Additon_Subtraction.v
//Created By: Sheetal Swaroop Burada
//Date: 30-04-2019
//Project Name: Design of 32 Bit Floating Point ALU Based on Standard IEEE-754 in Verilog and its implementation on FPGA.
//University: Dayalbagh Educational Institute
////////////////////////////////////////////////////////////////////////////////////////////////////////////////////
`include "Priority_Encoder.v"

`timescale 1ns/100ps

module Addition_Subtraction(
input [31:0] a_operand,b_operand, //Inputs in the format of IEEE-754 Representation.
input AddBar_Sub,				  //If Add_Sub is low then Addition else Subtraction.
output Exception,
output [31:0] result              //Outputs in the format of IEEE-754 Representation.
);

wire operation_sub_addBar;
wire Comp_enable;
wire output_sign;
wire perform;

wire [31:0] operand_a,operand_b;
wire [23:0] significand_a,significand_b;
wire [7:0] exponent_diff;


wire [23:0] significand_b_add_sub;
wire [7:0] exponent_b_add_sub;

wire [24:0] significand_add;
wire [30:0] add_sum;

wire [23:0] significand_sub_complement;
wire [24:0] significand_sub;
wire [30:0] sub_diff;
wire [24:0] subtraction_diff; 
wire [7:0] exponent_sub;

//for operations always operand_a must not be less than b_operand
assign {Comp_enable,operand_a,operand_b} = (a_operand[30:0] < b_operand[30:0]) ? {1'b1,b_operand,a_operand} : {1'b0,a_operand,b_operand};

//assign exp_a = operand_a[30:23];
//assign exp_b = operand_b[30:23];

//Exception flag sets 1 if either one of the exponent is 255.
assign Exception = (&operand_a[30:23]) | (&operand_b[30:23]);

assign output_sign = AddBar_Sub ? Comp_enable ? !operand_a[31] : operand_a[31] : operand_a[31] ;

assign operation_sub_addBar = AddBar_Sub ? operand_a[31] ^ operand_b[31] : ~(operand_a[31] ^ operand_b[31]);

//Assigining significand values according to Hidden Bit.
//If exponent is equal to zero then hidden bit will be 0 for that respective significand else it will be 1
assign significand_a = (|operand_a[30:23]) ? {1'b1,operand_a[22:0]} : {1'b0,operand_a[22:0]};
assign significand_b = (|operand_b[30:23]) ? {1'b1,operand_b[22:0]} : {1'b0,operand_b[22:0]};

//Evaluating Exponent Difference
assign exponent_diff = operand_a[30:23] - operand_b[30:23];

//Shifting significand_b according to exponent_diff
assign significand_b_add_sub = significand_b >> exponent_diff;

assign exponent_b_add_sub = operand_b[30:23] + exponent_diff; 

//Checking exponents are same or not
assign perform = (operand_a[30:23] == exponent_b_add_sub);

///////////////////////////////////////////////////////////////////////////////////////////////////////
//------------------------------------------------ADD BLOCK------------------------------------------//

assign significand_add = (perform & operation_sub_addBar) ? (significand_a + significand_b_add_sub) : 25'd0; 

//Result will be equal to Most 23 bits if carry generates else it will be Least 22 bits.
assign add_sum[22:0] = significand_add[24] ? significand_add[23:1] : significand_add[22:0];

//If carry generates in sum value then exponent must be added with 1 else feed as it is.
assign add_sum[30:23] = significand_add[24] ? (1'b1 + operand_a[30:23]) : operand_a[30:23];

///////////////////////////////////////////////////////////////////////////////////////////////////////
//------------------------------------------------SUB BLOCK------------------------------------------//

assign significand_sub_complement = (perform & !operation_sub_addBar) ? ~(significand_b_add_sub) + 24'd1 : 24'd0 ; 

assign significand_sub = perform ? (significand_a + significand_sub_complement) : 25'd0;

priority_encoder pe(significand_sub,operand_a[30:23],subtraction_diff,exponent_sub);

assign sub_diff[30:23] = exponent_sub;

assign sub_diff[22:0] = subtraction_diff[22:0];

///////////////////////////////////////////////////////////////////////////////////////////////////////
//-------------------------------------------------OUTPUT--------------------------------------------//

//If there is no exception and operation will evaluate


assign result = Exception ? 32'b0 : ((!operation_sub_addBar) ? {output_sign,sub_diff} : {output_sign,add_sum});

endmodule

code/e18-verilog-tb/src/mac.v
// MAC unit can process 4 input spikes together
// 4 spike inputs  
// 4 weights corresponding to the synapse

/*  Floating point addition
    Moving through the next four connections ?*/
`timescale 1ns/100ps

module mac(
    
    input wire CLK,                             //input clock
    input wire[11:0] neuron_address,            //neuron address
    input wire[11:0] source_address,            //source address of 12 bits
    input wire[159:0] weights_array,            //weights array used during intialization 32x5=160 bits
    input wire[59:0] source_addresses_array,          //corresponding source address array used during initialization 12x5=60 bits
    input wire clear,                       //signal to signify the end of the timestep
    output reg[31:0] mult_output               //output of 32 bits to the adder
    );             

    reg[3:0] i;                      //iterate through for the sources addresses
    reg[3:0] index;                  //get array index of the connection
    reg incoming_spikes[0:4];   //note incoming spikes
    reg spikes[0:4];            //received stored spikes
    reg[31:0] weights [0:4];    //array to store 5 weights
    reg[11:0] source_addresses [0:4];    //array to store corresponding 5 source addresses
    reg break;
    reg[31:0] accumulated_weight;   //get the accumulated weight
    reg[31:0] considered_weight;    //weight to be added
    wire[31:0] added_weight;         //weight
    wire exception;                 //addition exception

    //addition block to add weights
    Addition_Subtraction add1(accumulated_weight, considered_weight, 1'b0, excpetion, added_weight);

    always @(weights_array, source_addresses_array) begin
        //break up the weights
        weights[4] = weights_array[31:0];
        weights[3] = weights_array[63:32];
        weights[2] = weights_array[95:64];
        weights[1] = weights_array[127:96];
        weights[0] = weights_array[159:128];

        //break up the source adddresses
        source_addresses[4] = source_addresses_array[11:0];
        source_addresses[3] = source_addresses_array[23:12];
        source_addresses[2] = source_addresses_array[35:24];
        source_addresses[1] = source_addresses_array[47:36];
        source_addresses[0] = source_addresses_array[59:48];
    end

    //when a spike/source address comes in get index and mark the incoming spike array
    always @(source_address) begin

        //get index by going through the source addresses
        break = 1'b0;
        for(i=0; i<5; i=i+1) begin
            if (source_addresses[i] == source_address) begin
                index = i;
            end
        end

        incoming_spikes[index] = 1'b1;      //record the incoming spike
    end

    //when clear signal comes reset read the icnoming spike array and reset it
    always @(clear) begin
        case(clear)
            1'b1: begin
                for(i=0; i<5; i=i+1) begin      //reset the incoming spikes array
                    spikes[i] = incoming_spikes[i];     //store the incoming spikes
                    incoming_spikes[i] = 1'b0;
                end

                accumulated_weight = 32'd0;     //set accumulated value to 0
                considered_weight = 32'd0;      //weight addition is zero

                //at the begining of the timestep accumulate weights and send to the potential adder unit
                for(i=0; i<5; i=i+1) begin
                    if(spikes[i] == 1'b1) begin
                        #1
                        considered_weight <= weights[i];         
                        accumulated_weight <= added_weight;
                    end
                end
            end
        endcase
    end

    //added weight
    always @(added_weight) begin
        mult_output = added_weight;
    end


    initial begin
        //set incoming spikes array to zeros
        for(i=0; i<5; i=i+1) begin      
            spikes[i] = 1'b0;    
            incoming_spikes[i] = 1'b0;
        end
    end


    // reg [127:0] mask;           //mask varibale to mask the weight that needs to be added
    // reg [127:0] mult_ans;       //weight answer after masking
    // reg [127:0] weight;         //4 weights at once
    // // For floating point addition
    // wire excpetion1, excpetion2, exception3;
    // wire [31:0] add_val1, add_val2, add_val3;

    //at the beginning of a timestep

    // always @(posedge CLK) begin 
    //     case (spike_in) 
    //         4'd0:   mult_output = 32'b0;                  // No spikes in any of the 4 branches.
    //         4'd1: begin
    //             mask = 128'b0;
    //             mask[31:0] = 32'd4294967295;   
    //             mult_ans = weight & mask; 
    //         end
    //         4'd2: begin
    //             mask = 128'b0;
    //             mask[63:32] = 32'd4294967295;   
    //             mult_ans = weight & mask; 
    //         end
    //         4'd3: begin
    //             mask = 128'b0;
    //             mask[63:0] = 32'd4294967295;   
    //             mult_ans = weight & mask; 
    //         end
    //         4'd4: begin
    //             mask = 128'b0;
    //             mask[95:64] = 32'd4294967295;   
    //             mult_ans = weight & mask; 
    //         end
    //         4'd5: begin
    //             mask = 128'b0;
    //             mask[31:0] = 32'd4294967295; 
    //             mask[95:64] = 32'd4294967295;   
    //             mult_ans = weight & mask; 
    //         end
    //         4'd6: begin
    //             mask = 128'b0;
    //             mask[95:32] = 32'd4294967295;   
    //             mult_ans = weight & mask; 
    //         end
    //         4'd7: begin
    //             mask = 128'b0;
    //             mask[95:0] = 64'd4294967295;   
    //             mult_ans = weight & mask; 
    //         end
    //         4'd8: begin
    //             mask = 128'b0;
    //             mask[127:96] = 32'd4294967295;   
    //             mult_ans = weight & mask; 
    //         end
    //         4'd9: begin
    //             mask = 128'b0;
    //             mask[127:96] = 32'd4294967295;  
    //             mask[31:0] = 32'd4294967295;
    //             mult_ans = weight & mask; 
    //         end
    //         4'd10: begin
    //             mask = 128'b0;
    //             mask[127:96] = 32'd4294967295;  
    //             mask[63:32] = 32'd4294967295;
    //             mult_ans = weight & mask; 
    //         end
    //         4'd11: begin
    //             mask = 128'b0;
    //             mask[127:96] = 32'd4294967295;  
    //             mask[63:0] = 64'd4294967295;
    //             mult_ans = weight & mask; 
    //         end
    //         4'd12: begin
    //             mask = 128'b0;
    //             mask[127:64] = 64'd4294967295;
    //             mult_ans = weight & mask; 
    //         end
    //         4'd13: begin
    //             mask = 128'b0;
    //             mask[127:96] = 32'd4294967295;  
    //             mask[31:0] = 32'd4294967295;
    //             mult_ans = weight & mask; 
    //         end
    //         4'd14: begin
    //             mask = 128'b0;
    //             mask[127:32] = 96'd4294967295;
    //             mult_ans = weight & mask; 
    //         end
    //         4'd15: begin
    //             mult_ans = weight;
    //         end
    //         default:    mult_ans = 4'bx;
    //     endcase
        
    //     // mult_output = mult_ans[31:0] + mult_ans[63:32] + mult_ans[95:64] + mult_ans[127:96];
    //     // mult_output = add_val3;
    // end

    // Addition_Subtraction add1(mult_ans[31:0], mult_ans[63:32], 1'b0, excpetion1, add_val1);
    // Addition_Subtraction add2(add_val1, mult_ans[95:64], 1'b0, excpetion2, add_val2);
    // Addition_Subtraction add3(add_val2, mult_ans[127:96], 1'b0, exception3, add_val3);

    // always@(add_val3 or spike_in) begin
    //     mult_output = add_val3;
    // end

endmodule

code/e18-verilog-tb/src/mac_TESTBENCH.v
`timescale 1ns/100ps

module testbench;

    reg CLK;
    reg[3:0] CLK_count;
    reg[11:0] neuron_address;
    reg [11:0] source_address;
    reg[159:0] weights_array;
    reg[59:0] source_addresses_array;
    reg clear;
    wire [31:0] result;

    mac m1(CLK, neuron_address, source_address, weights_array, source_addresses_array, clear, result);

    // Print the outputs when ever the inputs change
    initial
    begin
        $monitor($time, "  source_address: %b           neuron_address: %b           result: %b              ", source_address, neuron_address, result);
    end

    // Observe the timing on gtkwave
    initial
    begin
        $dumpfile("mac_wavedata.vcd");
        $dumpvars(0,testbench);
    end

    initial
    // Assign the inputs
    begin 

        CLK = 1'b0;
        CLK_count = 0;
        clear = 1'b0;
        
        //send neuron addresses
        neuron_address = 12'b000000001000;

        //send source addresses array first
        source_addresses_array = {12'd3, 12'd4, 12'd5, 12'd6, 12'd7};

        //assign the weights
        weights_array = {32'h4290b333, 32'h41975c29, 32'h42470a3d, 32'h0, 32'h42ae3852};

        #40
        source_address = 12'd3;

        #4
        source_address = 12'd4;  

        #4
        source_address = 12'd5;

        #4
        source_address = 12'd7;       

        #100
        $finish;    

    end

    //invert clock every 4 seconds
    always
        #4 CLK = ~CLK;


    always @(posedge CLK) begin

        if(CLK_count==3) begin
            CLK_count=0;
            clear = 1'b1;
        end else begin
            CLK_count = CLK_count+1;
        end

        if(CLK_count==1) begin
            clear = 1'b0;
        end

    end

endmodule

code/e18-verilog-tb/src/mac_wavedata.vcd
$date
	Mon Apr  8 21:21:57 2024
$end
$version
	Icarus Verilog
$end
$timescale
	100ps
$end
$scope module testbench $end
$var wire 32 ! result [31:0] $end
$var reg 1 " CLK $end
$var reg 4 # CLK_count [3:0] $end
$var reg 1 $ clear $end
$var reg 12 % neuron_address [11:0] $end
$var reg 12 & source_address [11:0] $end
$var reg 60 ' source_addresses_array [59:0] $end
$var reg 160 ( weights_array [159:0] $end
$scope module m1 $end
$var wire 1 " CLK $end
$var wire 1 $ clear $end
$var wire 12 ) neuron_address [11:0] $end
$var wire 12 * source_address [11:0] $end
$var wire 60 + source_addresses_array [59:0] $end
$var wire 160 , weights_array [159:0] $end
$var wire 1 - excpetion $end
$var wire 32 . added_weight [31:0] $end
$var reg 32 / accumulated_weight [31:0] $end
$var reg 1 0 break $end
$var reg 32 1 considered_weight [31:0] $end
$var reg 4 2 i [3:0] $end
$var reg 4 3 index [3:0] $end
$var reg 32 4 mult_output [31:0] $end
$scope module add1 $end
$var wire 1 5 AddBar_Sub $end
$var wire 1 - Exception $end
$var wire 32 6 a_operand [31:0] $end
$var wire 32 7 b_operand [31:0] $end
$var wire 1 8 operation_sub_addBar $end
$var wire 1 9 output_sign $end
$var wire 25 : subtraction_diff [24:0] $end
$var wire 31 ; sub_diff [30:0] $end
$var wire 24 < significand_sub_complement [23:0] $end
$var wire 25 = significand_sub [24:0] $end
$var wire 24 > significand_b_add_sub [23:0] $end
$var wire 24 ? significand_b [23:0] $end
$var wire 25 @ significand_add [24:0] $end
$var wire 24 A significand_a [23:0] $end
$var wire 32 B result [31:0] $end
$var wire 1 C perform $end
$var wire 32 D operand_b [31:0] $end
$var wire 32 E operand_a [31:0] $end
$var wire 8 F exponent_sub [7:0] $end
$var wire 8 G exponent_diff [7:0] $end
$var wire 8 H exponent_b_add_sub [7:0] $end
$var wire 31 I add_sum [30:0] $end
$var wire 1 J Comp_enable $end
$scope module pe $end
$var wire 8 K Exponent_a [7:0] $end
$var wire 25 L significand [24:0] $end
$var wire 8 M Exponent_sub [7:0] $end
$var reg 25 N Significand [24:0] $end
$var reg 5 O shift [4:0] $end
$upscope $end
$upscope $end
$upscope $end
$upscope $end
$enddefinitions $end
#0
$dumpvars
bx O
bx N
bx M
bx L
bx K
xJ
bx I
bx H
bx G
bx F
bx E
bx D
xC
bx B
bx A
bx @
bx ?
bx >
bx =
bx <
bx ;
bx :
x9
x8
bx 7
bx 6
05
bx 4
bx 3
b101 2
bx 1
x0
bx /
bx .
x-
b100001010010000101100110011001101000001100101110101110000101001010000100100011100001010001111010000000000000000000000000000000001000010101011100011100001010010 ,
b11000000000100000000000101000000000110000000000111 +
bx *
b1000 )
b100001010010000101100110011001101000001100101110101110000101001010000100100011100001010001111010000000000000000000000000000000001000010101011100011100001010010 (
b11000000000100000000000101000000000110000000000111 '
bx &
b1000 %
0$
b0 #
0"
bx !
$end
#40
b1 #
1"
#80
0"
#120
b10 #
1"
#160
0"
#200
b11 #
1"
#240
0"
#280
b0 ;
b0 F
b0 M
b0 O
b0 :
b0 N
b0 =
b0 L
b0 <
b0 !
b0 4
b0 @
b0 .
b0 B
18
b0 >
b0 ?
0-
b0 A
b0 I
0J
1C
b0 H
b0 G
09
b0 K
b0 D
b0 E
b0 1
b0 7
b0 /
b0 6
b101 2
1$
b0 #
1"
#320
0"
#360
0$
b1 #
1"
#400
b0 3
b101 2
00
0"
b11 &
b11 *
#440
b10 #
b1 3
b101 2
1"
b100 &
b100 *
#480
b10 3
b101 2
0"
b101 &
b101 *
#520
b11 #
b100 3
b101 2
1"
b111 &
b111 *
#560
0"
#600
b0 2
1$
b0 #
1"
#610
b1000010100100001011001100110011 !
b1000010100100001011001100110011 4
b1011011110100110011001101 :
b1011011110100110011001101 N
b1000010100100001011001100110011 .
b1000010100100001011001100110011 B
b100100001011001100110011 @
b100100001011001100110011 =
b100100001011001100110011 L
b100100001011001100110011 A
b1000010100100001011001100110011 I
b0 >
b1000010111011110100110011001101 ;
b10000101 F
b10000101 M
b10000101 K
b0 ?
b1000010100100001011001100110011 E
1J
b10000101 G
1C
b10000101 H
b0 D
b1000010100100001011001100110011 1
b1000010100100001011001100110011 7
b1 2
#620
b1000010101101101000101000111101 !
b1000010101101101000101000111101 4
b1011011110100110011001101 :
b1011011110100110011001101 N
b1000010101101101000101000111101 .
b1000010101101101000101000111101 B
b101101101000101000111101 @
b100100001011001100110011 =
b100100001011001100110011 L
b1001011101011100001010 >
b100101110101110000101001 ?
b100100001011001100110011 A
b1000010101101101000101000111101 I
0J
b10000101 H
b10 G
1C
b1000010111011110100110011001101 ;
b10000101 F
b10000101 M
b10000101 K
b1000001100101110101110000101001 D
b1000010100100001011001100110011 E
b1000010100100001011001100110011 /
b1000010100100001011001100110011 6
b1000001100101110101110000101001 1
b1000001100101110101110000101001 7
b10 2
#630
b1000011000011010000011110101101 !
b1000011000011010000011110101101 4
b1000011000011010000011110101101 .
b1000011000011010000011110101101 B
b1000011000011010000011110101101 I
b1000010110010010111010111000011 ;
b1010010010111010111000011 :
b1010010010111010111000011 N
b110001110000101000111101 ?
b1000110100000111101011011 @
b101101101000101000111101 =
b101101101000101000111101 L
b101101101000101000111101 A
b11000111000010100011110 >
b1 G
1C
b10000101 H
b1000010010001110000101000111101 D
b1000010101101101000101000111101 E
b1000010101101101000101000111101 /
b1000010101101101000101000111101 6
b1000010010001110000101000111101 1
b1000010010001110000101000111101 7
b100 2
#640
b1000011011001000010001111010110 !
b1000011011001000010001111010110 4
b1011100101111100001010011 :
b1011100101111100001010011 N
b1000011011001000010001111010110 .
b1000011011001000010001111010110 B
b111001000010001111010110 @
b100011010000011110101101 =
b100011010000011110101101 L
b101011100011100001010010 ?
b100011010000011110101101 A
b1000011011001000010001111010110 I
b10101110001110000101001 >
b10000110 H
b1 G
1C
b1000011011100101111100001010011 ;
b10000110 F
b10000110 M
b10000110 K
b1000010101011100011100001010010 D
b1000011000011010000011110101101 E
b1000011000011010000011110101101 /
b1000011000011010000011110101101 6
b1000010101011100011100001010010 1
b1000010101011100011100001010010 7
b101 2
0"
#680
0$
b1 #
1"
#720
0"
#760
b10 #
1"
#800
0"
#840
b11 #
1"
#880
0"
#920
b0 !
b0 4
b0 :
b0 N
b0 .
b0 B
b0 =
b0 L
b0 ?
b0 A
b0 @
b0 I
b0 >
b0 H
b0 G
1C
b0 ;
b0 F
b0 M
b0 K
b0 D
b0 E
b0 1
b0 7
b0 /
b0 6
b101 2
1$
b0 #
1"
#960
0"
#1000
0$
b1 #
1"
#1040
0"
#1080
b10 #
1"
#1120
0"
#1160
b11 #
1"
#1200
0"
#1240
b101 2
1$
b0 #
1"
#1280
0"
#1320
0$
b1 #
1"
#1360
0"
#1400
b10 #
1"
#1440
0"
#1480
b11 #
1"
